sentinel/__init__.py
sentinel/board_detector.py
sentinel/cli.py
sentinel/command_router.py
sentinel/plugin_registry.py
sentinel/sdk.py
sentinel/slp_logger.py
sentinel/slp_protocol_handler.py
sentinel/hardware_backends/__init__.py
sentinel/hardware_backends/arduino.py
sentinel/hardware_backends/raspberry_pi.py
sentinel/llm_api/__init__.py
sentinel/llm_api/openai_llm.py
sentinel/plugins/__init__.py
sentinel/plugins/motor_control.py
sentinel/plugins/sensor_readers.py
sentinel/plugins/servo_control.py
sentinel_llm_sdk-0.1.0.dist-info/METADATA
sentinel_llm_sdk-0.1.0.dist-info/WHEEL
sentinel_llm_sdk-0.1.0.dist-info/entry_points.txt
sentinel_llm_sdk-0.1.0.dist-info/top_level.txt
sentinel_llm_sdk-0.1.0.dist-info/RECORD
